mouse_ran_down/__init__.py
mouse_ran_down/link_handling.py
mouse_ran_down/main.py
mouse_ran_down/mrd_logging.py
mouse_ran_down/requirements.txt
mouse_ran_down/sending.py
mouse_ran_down-0.0.6.dist-info/entry_points.txt
mouse_ran_down-0.0.6.dist-info/licenses/LICENSE
mouse_ran_down-0.0.6.dist-info/WHEEL
mouse_ran_down-0.0.6.dist-info/METADATA
mouse_ran_down-0.0.6.dist-info/RECORD
