Metadata-Version: 2.4
Name: mouse_ran_down
Version: 0.0.6
Summary: Bring media from shared links directly into Telegram chats.
Keywords: Bandcamp,Bluesky,Instagram,Mastodon,Reddit,SoundCloud,Telegram,TikTok,Twitter,Vimeo,X,YouTube,yt-dlp
Author: Andy Kluger
Requires-Python: >=3.13
Classifier: Programming Language :: Python :: 3.13
License-File: LICENSE
Requires-Dist: gallery-dl>1.29.5
Requires-Dist: html2text
Requires-Dist: instagrapi
Requires-Dist: instaloader
Requires-Dist: nestedtext
Requires-Dist: pillow
Requires-Dist: plumbum
Requires-Dist: pyTelegramBotAPI
Requires-Dist: stamina
Requires-Dist: structlog
Requires-Dist: yt-dlp[default, curl-cffi]>=2025.5.22
Requires-Dist: gallery-dl>1.29.5 ; extra == "dev"
Requires-Dist: html2text ; extra == "dev"
Requires-Dist: instagrapi ; extra == "dev"
Requires-Dist: instaloader ; extra == "dev"
Requires-Dist: ipython ; extra == "dev"
Requires-Dist: nestedtext ; extra == "dev"
Requires-Dist: pillow ; extra == "dev"
Requires-Dist: plumbum ; extra == "dev"
Requires-Dist: pyTelegramBotAPI ; extra == "dev"
Requires-Dist: pyright ; extra == "dev"
Requires-Dist: rich ; extra == "dev"
Requires-Dist: ruff ; extra == "dev"
Requires-Dist: sentry-sdk ; extra == "dev"
Requires-Dist: ssort ; extra == "dev"
Requires-Dist: stamina ; extra == "dev"
Requires-Dist: structlog ; extra == "dev"
Requires-Dist: structlog-sentry ; extra == "dev"
Requires-Dist: yt-dlp[default, curl-cffi]>=2025.5.22 ; extra == "dev"
Requires-Dist: sentry-sdk ; extra == "sentry"
Requires-Dist: structlog-sentry ; extra == "sentry"
Project-URL: Home, https://github.com/AndydeCleyre/mouse-ran-down
Provides-Extra: dev
Provides-Extra: sentry
